{
  "name": "cuberoom",
  "dimensions": [2, 5, 2],
  "color": [0.4, 0.5, 0.6],
  "portals": [
    {
      "name": "0",
      "position": [1, 0, 0],
      "angle": 0,
      "rule": "hallways"
    },
    {
      "name": "1",
      "position": [0, 0, 1],
      "angle": 90,
      "rule": "hallways"
    },
    {
      "name": "2",
      "position": [1, 0, 2],
      "angle": 180,
      "rule": "hallways"
    },
    {
      "name": "3",
      "position": [2, 0, 1],
      "angle": 270,
      "rule": "hallways"
    }
  ]
}